CHANGELOG.txt
LICENSE.txt
MANIFEST.in
README.txt
setup.py
dnsbl.egg-info/PKG-INFO
dnsbl.egg-info/SOURCES.txt
dnsbl.egg-info/dependency_links.txt
dnsbl.egg-info/requires.txt
dnsbl.egg-info/top_level.txt
dnsbl_check/__init__.py