Metadata-Version: 1.1
Name: dnsbl
Version: 0.0.4
Summary: Module that checks the given ips blacklisting status
Home-page: UNKNOWN
Author: Aswin venkat
Author-email: aswin.venkat@cybersecurityworks.com
License: MIT
Keywords: dnsbl
Platform: UNKNOWN
Classifier: Development Status :: 5 - Production/Stable
Classifier: Intended Audience :: Education
Classifier: Operating System :: Microsoft :: Windows :: Windows 10
Classifier: License :: OSI Approved :: MIT License
Classifier: Programming Language :: Python :: 3
